py2docfx/__init__.py
py2docfx/__main__.py
py2docfx/convert_prepare/__init__.py
py2docfx/convert_prepare/environment.py
py2docfx/convert_prepare/generate_conf.py
py2docfx/convert_prepare/generate_document.py
py2docfx/convert_prepare/get_source.py
py2docfx/convert_prepare/git.py
py2docfx/convert_prepare/install_package.py
py2docfx/convert_prepare/pack.py
py2docfx/convert_prepare/package_info.py
py2docfx/convert_prepare/package_info_extra_settings.py
py2docfx/convert_prepare/params.py
py2docfx/convert_prepare/paths.py
py2docfx/convert_prepare/pip_utils.py
py2docfx/convert_prepare/repo_info.py
py2docfx/convert_prepare/source.py
py2docfx/convert_prepare/sphinx_caller.py
py2docfx/convert_prepare/subpackage.py
py2docfx/convert_prepare/conf_templates/conf.py_t
py2docfx/convert_prepare/conf_templates/master_doc.rst_t
py2docfx/convert_prepare/post_process/merge_toc.py
py2docfx/convert_prepare/subpackage_merge/merge_root_package.py
py2docfx/convert_prepare/subpackage_merge/merge_toc.py
py2docfx/convert_prepare/tests/__init__.py
py2docfx/convert_prepare/tests/test_generate_document.py
py2docfx/convert_prepare/tests/test_get_source.py
py2docfx/convert_prepare/tests/test_pack.py
py2docfx/convert_prepare/tests/test_package_info.py
py2docfx/convert_prepare/tests/test_params.py
py2docfx/convert_prepare/tests/test_post_process_merge_toc.py
py2docfx/convert_prepare/tests/test_source.py
py2docfx/convert_prepare/tests/test_sphinx_caller.py
py2docfx/convert_prepare/tests/test_subpackage.py
py2docfx/convert_prepare/tests/data/generate_document/azure-dummy-sourcecode/__init__.py
py2docfx/convert_prepare/tests/data/generate_document/azure-dummy-sourcecode/azure/__init__.py
py2docfx/convert_prepare/tests/data/generate_document/azure-dummy-sourcecode/azure/dummy/__init__.py
py2docfx/convert_prepare/tests/data/generate_document/azure-dummy-sourcecode/azure/dummy/sourcecode/__init__.py
py2docfx-0.1.11.dist-info/METADATA
py2docfx-0.1.11.dist-info/WHEEL
py2docfx-0.1.11.dist-info/top_level.txt
py2docfx-0.1.11.dist-info/RECORD
